mir/acle/__init__.py
mir/acle/base.py
mir/acle/handlers.py
mir.acle-2.0.0.dist-info/DESCRIPTION.rst
mir.acle-2.0.0.dist-info/METADATA
mir.acle-2.0.0.dist-info/RECORD
mir.acle-2.0.0.dist-info/WHEEL
mir.acle-2.0.0.dist-info/metadata.json
mir.acle-2.0.0.dist-info/top_level.txt
