Metadata-Version: 2.0
Name: mir.acle
Version: 2.0.0
Summary: Distribution template for the mir namespace
Home-page: https://github.com/darkfeline/mir.acle
Author: Allen Li
Author-email: darkfeline@felesatra.moe
License: UNKNOWN
Platform: UNKNOWN
Classifier: Development Status :: 3 - Alpha
Classifier: Intended Audience :: Developers
Classifier: License :: OSI Approved :: Apache Software License
Classifier: Programming Language :: Python :: 3.6
